holyshit_eso/__init__.py
holyshit_eso/hs.py
holyshit_eso/interpreter.py
holyshit_eso/lexer.py
holyshit_eso/parser.py
holyshit_eso-1.0.3.dist-info/METADATA
holyshit_eso-1.0.3.dist-info/WHEEL
holyshit_eso-1.0.3.dist-info/entry_points.txt
holyshit_eso-1.0.3.dist-info/top_level.txt
holyshit_eso-1.0.3.dist-info/RECORD
