Metadata-Version: 2.4
Name: holyshit_eso
Version: 1.0.3
Summary: A terribly written esolang inspired by BrainF*ck
Author-email: BravestCheetah <bravestcheetah@gmail.com>
Project-URL: Homepage, https://github.com/BravestCheetah/holyshit-esolang
Project-URL: Bug Tracker, https://github.com/BravestCheetah/holyshit-esolang/issues
Classifier: Programming Language :: Python :: 3
Classifier: License :: OSI Approved :: MIT License
Classifier: Operating System :: OS Independent
Requires-Python: >=3.12
Requires-Dist: termcolor
